django_syauth/__init__.py
django_syauth/apps.py
django_syauth/backend.py
django_syauth/decorators.py
django_syauth/middleware.py
django_syauth/urls.py
django_syauth/utils.py
django_syauth/views.py
django_syauth-0.1.0.dist-info/licenses/LICENSE
django_syauth-0.1.0.dist-info/METADATA
django_syauth-0.1.0.dist-info/WHEEL
django_syauth-0.1.0.dist-info/top_level.txt
django_syauth-0.1.0.dist-info/RECORD
