Metadata-Version: 2.4
Name: django-syauth
Version: 0.1.0
Summary: Official Django SDK for Syauth Authentication
Author-email: Nexorix <support@nexorix.com>
License: MIT License
Project-URL: Homepage, https://syauth.com
Project-URL: Documentation, https://developers.nexorix.com/syauth
Project-URL: Repository, https://github.com/nexorix/django-syauth
Project-URL: Issues, https://github.com/nexorix/django-syauth/issues
Project-URL: Changelog, https://github.com/nexorix/django-syauth/blob/main/CHANGELOG.md
Keywords: django,authentication,oauth,oidc,syauth,sso
Classifier: Development Status :: 4 - Beta
Classifier: Framework :: Django
Classifier: Framework :: Django :: 4.0
Classifier: Framework :: Django :: 4.1
Classifier: Framework :: Django :: 4.2
Classifier: Framework :: Django :: 5.0
Classifier: Intended Audience :: Developers
Classifier: License :: OSI Approved :: MIT License
Classifier: Programming Language :: Python :: 3
Classifier: Programming Language :: Python :: 3.8
Classifier: Programming Language :: Python :: 3.9
Classifier: Programming Language :: Python :: 3.10
Classifier: Programming Language :: Python :: 3.11
Classifier: Programming Language :: Python :: 3.12
Classifier: Topic :: Internet :: WWW/HTTP :: Session
Classifier: Topic :: Security
Requires-Python: >=3.8
License-File: LICENSE
Requires-Dist: django>=4.0
Requires-Dist: requests>=2.25.0
Requires-Dist: pyjwt[crypto]>=2.8.0
Dynamic: license-file
